{
  "entries": {
    "tap": {
      "dart-lang/dart": {
        "revision": "98ef4c2c2311eaa54d1be3679808aea63d7bcb23"
      },
      "getantibody/tap": {
        "revision": "5afaacbc3c33bdafb797d72ddfe40f007f79dfde"
      },
      "homebrew/bundle": {
        "revision": "cf856030d1d823bbfe8c6c26074745a7d89f13d7"
      },
      "homebrew/cask": {
        "revision": "897531f175818280cc6607f0503d66a35b8ff579"
      },
      "homebrew/core": {
        "revision": "b82ebf7f81d0e9790e46d14d0786d666664ace12"
      },
      "homebrew/services": {
        "revision": "5d9721075f2b538e29ea4022ff666afa7065f164"
      },
      "miderwong/flutter": {
        "revision": "e2e0c773ea813129b75994c9a2fe3f6f8c61c560"
      }
    },
    "brew": {
      "atlassian-cli": {
        "version": "9.0.0",
        "bottle": false
      },
      "cocoapods": {
        "version": "1.8.4",
        "bottle": {
          "cellar": ":any_skip_relocation",
          "prefix": "/usr/local",
          "files": {
            "catalina": {
              "url": "https://homebrew.bintray.com/bottles/cocoapods-1.8.4.catalina.bottle.tar.gz",
              "sha256": "d3a1e25ecbb970fb8c560eb382d2ad638e91e3904079ab5927ad949fbdfcdd4c"
            },
            "mojave": {
              "url": "https://homebrew.bintray.com/bottles/cocoapods-1.8.4.mojave.bottle.tar.gz",
              "sha256": "d43db56c6e712b2ea5349d1fd02cb60678d7becc2672921132408498aa20adc2"
            },
            "high_sierra": {
              "url": "https://homebrew.bintray.com/bottles/cocoapods-1.8.4.high_sierra.bottle.tar.gz",
              "sha256": "29ed00f2a077cb02c4bc224738c2a6e1447cbe0b78112db3bc68f583d466506f"
            }
          }
        }
      },
      "fzf": {
        "version": "0.19.0",
        "bottle": {
          "cellar": ":any_skip_relocation",
          "prefix": "/usr/local",
          "files": {
            "catalina": {
              "url": "https://homebrew.bintray.com/bottles/fzf-0.19.0.catalina.bottle.tar.gz",
              "sha256": "0be169ab230f6ff7b2322ee3d61fa0cd44e04300b688d207b67e910d948af442"
            },
            "mojave": {
              "url": "https://homebrew.bintray.com/bottles/fzf-0.19.0.mojave.bottle.tar.gz",
              "sha256": "5b5f429819576c27bab7bb658e3a99ae8043535e19d887fd9eaee954667ee715"
            },
            "high_sierra": {
              "url": "https://homebrew.bintray.com/bottles/fzf-0.19.0.high_sierra.bottle.tar.gz",
              "sha256": "19e9ba86b09129e06530b322f892ba89fb1db3173219ca0228cc0fe2d8281fbc"
            }
          }
        }
      },
      "git": {
        "version": "2.24.0_2",
        "bottle": {
          "cellar": "/usr/local/Cellar",
          "prefix": "/usr/local",
          "files": {
            "catalina": {
              "url": "https://homebrew.bintray.com/bottles/git-2.24.0_2.catalina.bottle.tar.gz",
              "sha256": "87100f6c01be17be5501be0ee5d674610e594ee0ae2d57ac3a2ebefec601e589"
            },
            "mojave": {
              "url": "https://homebrew.bintray.com/bottles/git-2.24.0_2.mojave.bottle.tar.gz",
              "sha256": "343c1a0b842b84095aa0632ea7ca3f1717103fe4f393a6014c7f6165b079c849"
            },
            "high_sierra": {
              "url": "https://homebrew.bintray.com/bottles/git-2.24.0_2.high_sierra.bottle.tar.gz",
              "sha256": "c4c40270f2acd82234660d8e1b3093294222fd8dc47687fc575815ed8544baf0"
            }
          }
        }
      },
      "go": {
        "version": "1.13.4",
        "bottle": {
          "cellar": "/usr/local/Cellar",
          "prefix": "/usr/local",
          "files": {
            "catalina": {
              "url": "https://homebrew.bintray.com/bottles/go-1.13.4.catalina.bottle.tar.gz",
              "sha256": "77af3e8081a002c86b4b87ec97dc5dc28cab49704913a4db22ebc7ce838dc6ad"
            },
            "mojave": {
              "url": "https://homebrew.bintray.com/bottles/go-1.13.4.mojave.bottle.tar.gz",
              "sha256": "2fc74073a90a7073dab940868ac23fa6cd465af8a39ed2d882b18d62bec2265f"
            },
            "high_sierra": {
              "url": "https://homebrew.bintray.com/bottles/go-1.13.4.high_sierra.bottle.tar.gz",
              "sha256": "20d5242dbbb08128c254a1cc96f55cfc9add74c9567600dfd9366f3d028f5563"
            }
          }
        }
      },
      "htop": {
        "version": "2.2.0_1",
        "bottle": {
          "cellar": ":any",
          "prefix": "/usr/local",
          "files": {
            "catalina": {
              "url": "https://homebrew.bintray.com/bottles/htop-2.2.0_1.catalina.bottle.tar.gz",
              "sha256": "c06ff60960f64f5c8395f53d7419cbcce2a22ee87f0cb0138352c8a88111d21c"
            },
            "mojave": {
              "url": "https://homebrew.bintray.com/bottles/htop-2.2.0_1.mojave.bottle.tar.gz",
              "sha256": "77aa302765353b4085dcad52356d3264183e06310dda8d5bac64642299ea2902"
            },
            "high_sierra": {
              "url": "https://homebrew.bintray.com/bottles/htop-2.2.0_1.high_sierra.bottle.tar.gz",
              "sha256": "0ebfb655b91566ba31f8effc94d642a43305ff95bdc9b30b46fadc132e2ced0c"
            },
            "sierra": {
              "url": "https://homebrew.bintray.com/bottles/htop-2.2.0_1.sierra.bottle.tar.gz",
              "sha256": "ed93b86f011de155c5d261b8c9cc9cb81fd0017667bf3ebe26ee090716bcd650"
            }
          }
        }
      },
      "usbmuxd": {
        "options": {
          "args": [
            "HEAD"
          ]
        }
      },
      "libimobiledevice": {
        "version": "HEAD-9f79242_6",
        "bottle": {
          "cellar": ":any",
          "prefix": "/usr/local",
          "files": {
            "catalina": {
              "url": "https://homebrew.bintray.com/bottles/libimobiledevice-HEAD-9f79242_6.catalina.bottle.tar.gz",
              "sha256": "27409d27b5532a572a4a8eeec891e1cce92bc0afa423528eae94543f22aa72aa"
            },
            "mojave": {
              "url": "https://homebrew.bintray.com/bottles/libimobiledevice-HEAD-9f79242_6.mojave.bottle.tar.gz",
              "sha256": "672ac6aaf5656e07add1b5da7c3a30c0655ce2b9efff957faa34855ed34d9dde"
            },
            "high_sierra": {
              "url": "https://homebrew.bintray.com/bottles/libimobiledevice-HEAD-9f79242_6.high_sierra.bottle.tar.gz",
              "sha256": "14e8fb93dbb63ceca4c66163d1f9bfe7db5bcbc581ae4ca3e3cc8dc0ab93eeb4"
            }
          }
        },
        "options": {
          "args": [
            "HEAD"
          ]
        }
      },
      "ideviceinstaller": {
        "version": "1.1.0_4",
        "bottle": {
          "cellar": ":any",
          "prefix": "/usr/local",
          "files": {
            "catalina": {
              "url": "https://homebrew.bintray.com/bottles/ideviceinstaller-1.1.0_4.catalina.bottle.1.tar.gz",
              "sha256": "3fcfe52042361034d6d884268c6e145db6ccae21a65d55fae590b8d3203209e6"
            },
            "mojave": {
              "url": "https://homebrew.bintray.com/bottles/ideviceinstaller-1.1.0_4.mojave.bottle.1.tar.gz",
              "sha256": "e0df189964f8d77e2ea30e8255b7d5a6fa82710b9b65e1351f086358530f6d84"
            },
            "high_sierra": {
              "url": "https://homebrew.bintray.com/bottles/ideviceinstaller-1.1.0_4.high_sierra.bottle.1.tar.gz",
              "sha256": "d8f6c9528b2737db5453b118e8792533274df7b06968c868ba0096cf62e48079"
            }
          }
        }
      },
      "ios-deploy": {
        "version": "1.9.4",
        "bottle": {
          "cellar": ":any_skip_relocation",
          "prefix": "/usr/local",
          "files": {
            "mojave": {
              "url": "https://homebrew.bintray.com/bottles/ios-deploy-1.9.4.mojave.bottle.tar.gz",
              "sha256": "43b17fb8423e24b280873044eebe7100bb0788f7fca80e4e48062a73f6183de9"
            },
            "high_sierra": {
              "url": "https://homebrew.bintray.com/bottles/ios-deploy-1.9.4.high_sierra.bottle.tar.gz",
              "sha256": "92be61884aeaa78e0571ec9764e841831c513733319c5b42439bda26640877c6"
            },
            "sierra": {
              "url": "https://homebrew.bintray.com/bottles/ios-deploy-1.9.4.sierra.bottle.tar.gz",
              "sha256": "8e46be474d63299f12cef533429a4c77a52d5a4872b79e29c47acf47d673d2ef"
            }
          }
        }
      },
      "jq": {
        "version": "1.6",
        "bottle": {
          "cellar": ":any",
          "prefix": "/usr/local",
          "files": {
            "catalina": {
              "url": "https://homebrew.bintray.com/bottles/jq-1.6.catalina.bottle.1.tar.gz",
              "sha256": "820a3c85fcbb63088b160c7edf125d7e55fc2c5c1d51569304499c9cc4b89ce8"
            },
            "mojave": {
              "url": "https://homebrew.bintray.com/bottles/jq-1.6.mojave.bottle.1.tar.gz",
              "sha256": "71f0e76c5b22e5088426c971d5e795fe67abee7af6c2c4ae0cf4c0eb98ed21ff"
            },
            "high_sierra": {
              "url": "https://homebrew.bintray.com/bottles/jq-1.6.high_sierra.bottle.1.tar.gz",
              "sha256": "dffcffa4ea13e8f0f2b45c5121e529077e135ae9a47254c32182231662ee9b72"
            },
            "sierra": {
              "url": "https://homebrew.bintray.com/bottles/jq-1.6.sierra.bottle.1.tar.gz",
              "sha256": "bb4d19dc026c2d72c53eed78eaa0ab982e9fcad2cd2acc6d13e7a12ff658e877"
            }
          }
        }
      },
      "kubernetes-cli": {
        "version": "1.16.3",
        "bottle": {
          "cellar": ":any_skip_relocation",
          "prefix": "/usr/local",
          "files": {
            "catalina": {
              "url": "https://homebrew.bintray.com/bottles/kubernetes-cli-1.16.3.catalina.bottle.tar.gz",
              "sha256": "0ffd9ee9bb5026ae526a09fe50591a94a1a987f52c5866e32aefb79b533f6e10"
            },
            "mojave": {
              "url": "https://homebrew.bintray.com/bottles/kubernetes-cli-1.16.3.mojave.bottle.tar.gz",
              "sha256": "b8999e5c544b70b0223952fd92eda08eff8035762dae2a27c31aaca24fed51c0"
            },
            "high_sierra": {
              "url": "https://homebrew.bintray.com/bottles/kubernetes-cli-1.16.3.high_sierra.bottle.tar.gz",
              "sha256": "a97a579a2adaa9720aa122355b0a43cbebea49da394f3489a300f41d8d5e7f77"
            }
          }
        }
      },
      "leiningen": {
        "version": "2.9.1",
        "bottle": {
          "cellar": ":any_skip_relocation",
          "prefix": "/usr/local",
          "files": {
            "catalina": {
              "url": "https://homebrew.bintray.com/bottles/leiningen-2.9.1.catalina.bottle.tar.gz",
              "sha256": "480cf69d0f2f9d43879b0768018ef323426d0cca145e00984d76890c2baaa919"
            },
            "mojave": {
              "url": "https://homebrew.bintray.com/bottles/leiningen-2.9.1.mojave.bottle.tar.gz",
              "sha256": "4b353034cd7bf4825ed9c5a340a20beed7382a8369f9ecd9f7da233e9b36a03a"
            },
            "high_sierra": {
              "url": "https://homebrew.bintray.com/bottles/leiningen-2.9.1.high_sierra.bottle.tar.gz",
              "sha256": "4b353034cd7bf4825ed9c5a340a20beed7382a8369f9ecd9f7da233e9b36a03a"
            },
            "sierra": {
              "url": "https://homebrew.bintray.com/bottles/leiningen-2.9.1.sierra.bottle.tar.gz",
              "sha256": "f7ebcf91cfac411472d2dfdee71f008bc2ad3d7289b342a98db0916e74b7f615"
            }
          }
        }
      },
      "neovim": {
        "version": "0.4.3",
        "bottle": {
          "cellar": "/usr/local/Cellar",
          "prefix": "/usr/local",
          "files": {
            "catalina": {
              "url": "https://homebrew.bintray.com/bottles/neovim-0.4.3.catalina.bottle.tar.gz",
              "sha256": "389ab254794ea04df8a106bf281c227c4fdee27c609d52951f32b9a0239031d6"
            },
            "mojave": {
              "url": "https://homebrew.bintray.com/bottles/neovim-0.4.3.mojave.bottle.tar.gz",
              "sha256": "fb6cc38c45be4650a4a750a314cec27f6f7643dc7c22a1f5abae347e1b39b388"
            },
            "high_sierra": {
              "url": "https://homebrew.bintray.com/bottles/neovim-0.4.3.high_sierra.bottle.tar.gz",
              "sha256": "b2f7450e005f4eb22bfaf650fe7741fa8629393a947b4dd48c9f91e7fc258113"
            }
          }
        }
      },
      "oath-toolkit": {
        "version": "2.6.2_1",
        "bottle": {
          "cellar": "/usr/local/Cellar",
          "prefix": "/usr/local",
          "files": {
            "catalina": {
              "url": "https://homebrew.bintray.com/bottles/oath-toolkit-2.6.2_1.catalina.bottle.1.tar.gz",
              "sha256": "24a65399ed4b462a3291c542616e1a5dad4df008dcb116fd12c34030f05135b0"
            },
            "mojave": {
              "url": "https://homebrew.bintray.com/bottles/oath-toolkit-2.6.2_1.mojave.bottle.1.tar.gz",
              "sha256": "ab9cbc2e7e8c7004c5a3db7fbc4b6a0cbc9560a353a306cba0fa4d1174a46f68"
            },
            "high_sierra": {
              "url": "https://homebrew.bintray.com/bottles/oath-toolkit-2.6.2_1.high_sierra.bottle.1.tar.gz",
              "sha256": "a7fbff2831b4c6a61896c65b482b3db50d2e070e1e74772e7fb929bbd4a586f0"
            }
          }
        }
      },
      "p7zip": {
        "version": "16.02_2",
        "bottle": {
          "cellar": ":any_skip_relocation",
          "prefix": "/usr/local",
          "files": {
            "catalina": {
              "url": "https://homebrew.bintray.com/bottles/p7zip-16.02_2.catalina.bottle.tar.gz",
              "sha256": "b9f5fb1321ce5738d0129b3c48f51fc36a947bd84450f95ce9caa90e767fbd1b"
            },
            "mojave": {
              "url": "https://homebrew.bintray.com/bottles/p7zip-16.02_2.mojave.bottle.tar.gz",
              "sha256": "0de20c4bd05dc5652ca5f188895bf74e52eb701aaed502a0d1271eb58236f898"
            },
            "high_sierra": {
              "url": "https://homebrew.bintray.com/bottles/p7zip-16.02_2.high_sierra.bottle.tar.gz",
              "sha256": "5951a42bd864da7dba5ef5781a2efba206daba8b6f75c60c0cfd910dae218482"
            },
            "sierra": {
              "url": "https://homebrew.bintray.com/bottles/p7zip-16.02_2.sierra.bottle.tar.gz",
              "sha256": "73fe6276e906f67cd28adc0f5a22c914d57fd3cfdd54134ad64e5330f710235a"
            }
          }
        }
      },
      "pidcat": {
        "version": "2.1.0",
        "bottle": false
      },
      "postgresql": {
        "version": "12.1",
        "bottle": {
          "cellar": "/usr/local/Cellar",
          "prefix": "/usr/local",
          "files": {
            "catalina": {
              "url": "https://homebrew.bintray.com/bottles/postgresql-12.1.catalina.bottle.tar.gz",
              "sha256": "309377407d7cb766d238f063c10210c4e48d48fcdadd62560346c2d4af782bc4"
            },
            "mojave": {
              "url": "https://homebrew.bintray.com/bottles/postgresql-12.1.mojave.bottle.tar.gz",
              "sha256": "2e97d7d591916d79f8e8a5ed0023c6d1e31e27a5b289d31d9b5cdf51e1d3a040"
            },
            "high_sierra": {
              "url": "https://homebrew.bintray.com/bottles/postgresql-12.1.high_sierra.bottle.tar.gz",
              "sha256": "754aac4d7055bdd801f91eef7e36ba93ee5fafd931e0a13a02bcd64e71ff34a9"
            }
          }
        },
        "options": {
          "restart_service": true
        }
      },
      "rbenv": {
        "version": "1.1.2",
        "bottle": {
          "cellar": ":any",
          "prefix": "/usr/local",
          "files": {
            "catalina": {
              "url": "https://homebrew.bintray.com/bottles/rbenv-1.1.2.catalina.bottle.tar.gz",
              "sha256": "503ed6d818502f00f031b9f49461934e252b9bfba2876e90a326fc27bb1052d6"
            },
            "mojave": {
              "url": "https://homebrew.bintray.com/bottles/rbenv-1.1.2.mojave.bottle.tar.gz",
              "sha256": "d1019098dee8d037587069398e5ad04e6d736f834dc44ae73943bec46b10b260"
            },
            "high_sierra": {
              "url": "https://homebrew.bintray.com/bottles/rbenv-1.1.2.high_sierra.bottle.tar.gz",
              "sha256": "b5984102794a9d39388ca1f6ec77965aeea29b971cc00cb5af8ede8ee6c926d6"
            },
            "sierra": {
              "url": "https://homebrew.bintray.com/bottles/rbenv-1.1.2.sierra.bottle.tar.gz",
              "sha256": "873175a851e5aa4f5b3438072030b945c252f08a9a07760c64dc045e2cce4724"
            }
          }
        }
      },
      "redis": {
        "version": "5.0.7",
        "bottle": {
          "cellar": ":any_skip_relocation",
          "prefix": "/usr/local",
          "files": {
            "catalina": {
              "url": "https://homebrew.bintray.com/bottles/redis-5.0.7.catalina.bottle.tar.gz",
              "sha256": "7a50c626ad90c40fd315f7f053460f0c6701cc2b776a1b3e83dc44698936cd0f"
            },
            "mojave": {
              "url": "https://homebrew.bintray.com/bottles/redis-5.0.7.mojave.bottle.tar.gz",
              "sha256": "e8956553dbc1f519bcd0330bd2d41eb884997303b84dd43be686a9d974e2d003"
            },
            "high_sierra": {
              "url": "https://homebrew.bintray.com/bottles/redis-5.0.7.high_sierra.bottle.tar.gz",
              "sha256": "789cf8094a5909d295ce3b9996b8470d565e6c9dedbc952176af670a660a8c6f"
            }
          }
        }
      },
      "screenfetch": {
        "version": "3.9.1",
        "bottle": false
      },
      "skaffold": {
        "version": "1.0.1",
        "bottle": {
          "cellar": ":any_skip_relocation",
          "prefix": "/usr/local",
          "files": {
            "catalina": {
              "url": "https://homebrew.bintray.com/bottles/skaffold-1.0.1.catalina.bottle.tar.gz",
              "sha256": "1031e97a764eacc50f8dfbf10dad488df26c181d896669909191b254cb5af255"
            },
            "mojave": {
              "url": "https://homebrew.bintray.com/bottles/skaffold-1.0.1.mojave.bottle.tar.gz",
              "sha256": "916892170e909e7dea00d7bc8f4267d41eeb00a2348bb88d69b05a24a55d6875"
            },
            "high_sierra": {
              "url": "https://homebrew.bintray.com/bottles/skaffold-1.0.1.high_sierra.bottle.tar.gz",
              "sha256": "6eef6b367f2ec486862b50f929daa41fdb13583e4e990dd3e1c517e643d405e0"
            }
          }
        }
      },
      "the_silver_searcher": {
        "version": "2.2.0",
        "bottle": {
          "cellar": ":any",
          "prefix": "/usr/local",
          "files": {
            "catalina": {
              "url": "https://homebrew.bintray.com/bottles/the_silver_searcher-2.2.0.catalina.bottle.tar.gz",
              "sha256": "6fd80fdd0896dae09c01d3c9785ddd658bb5f2f229e7d011d3fbdde887bc35d0"
            },
            "mojave": {
              "url": "https://homebrew.bintray.com/bottles/the_silver_searcher-2.2.0.mojave.bottle.tar.gz",
              "sha256": "e57f89664f48c131dfb462dc4be2f5265867d827f82efb1c3841ba71d9156ed0"
            },
            "high_sierra": {
              "url": "https://homebrew.bintray.com/bottles/the_silver_searcher-2.2.0.high_sierra.bottle.tar.gz",
              "sha256": "0bf5394d8ab5f61b8fbb593249f556f13b358d16eb0d3c97215be3da0476e94b"
            },
            "sierra": {
              "url": "https://homebrew.bintray.com/bottles/the_silver_searcher-2.2.0.sierra.bottle.tar.gz",
              "sha256": "2365e24e5d0b1bef64b35c6a8f9e4f61d1f38eafe38c06d6e0acefc6a9a955db"
            },
            "el_capitan": {
              "url": "https://homebrew.bintray.com/bottles/the_silver_searcher-2.2.0.el_capitan.bottle.tar.gz",
              "sha256": "1f35dcee133d638a16462db711560b624020e9dd8f732ac5a6f13a09b694421a"
            }
          }
        }
      },
      "tig": {
        "version": "2.5.0",
        "bottle": {
          "cellar": ":any",
          "prefix": "/usr/local",
          "files": {
            "catalina": {
              "url": "https://homebrew.bintray.com/bottles/tig-2.5.0.catalina.bottle.tar.gz",
              "sha256": "03f5fc99e3763dc90dd4e2a3445fb9e4a65a2db790b8aa40c1d56cd08d1d5f6f"
            },
            "mojave": {
              "url": "https://homebrew.bintray.com/bottles/tig-2.5.0.mojave.bottle.tar.gz",
              "sha256": "5fbd4ddf058724d51f88221bb54f949dd79941d7654f63881c62bf9768a7e12e"
            },
            "high_sierra": {
              "url": "https://homebrew.bintray.com/bottles/tig-2.5.0.high_sierra.bottle.tar.gz",
              "sha256": "8c85a68d1ff0400649e18b47160152ea1220e72afa6217d916462ecc7053bf14"
            }
          }
        }
      },
      "unrar": {
        "version": "5.8.4",
        "bottle": {
          "cellar": ":any",
          "prefix": "/usr/local",
          "files": {
            "catalina": {
              "url": "https://homebrew.bintray.com/bottles/unrar-5.8.4.catalina.bottle.tar.gz",
              "sha256": "0cd15d4c8a60379e3eac65260a8fddc8c99ce650214c61b94de35502a17dc44e"
            },
            "mojave": {
              "url": "https://homebrew.bintray.com/bottles/unrar-5.8.4.mojave.bottle.tar.gz",
              "sha256": "cb33b0c6fa82e4d01483bcc7398bf4a7e15e1b6cd0eb78ae177965237d52eb9d"
            },
            "high_sierra": {
              "url": "https://homebrew.bintray.com/bottles/unrar-5.8.4.high_sierra.bottle.tar.gz",
              "sha256": "59b6e3808c99fbc8c6edca2f76c8e2b198a68ffda0a2c4e2f44328f89b049613"
            }
          }
        }
      },
      "wget": {
        "version": "1.20.3_2",
        "bottle": {
          "cellar": "/usr/local/Cellar",
          "prefix": "/usr/local",
          "files": {
            "catalina": {
              "url": "https://homebrew.bintray.com/bottles/wget-1.20.3_2.catalina.bottle.tar.gz",
              "sha256": "ef65c759c5097a36323fa9c77756468649e8d1980a3a4e05695c05e39568967c"
            },
            "mojave": {
              "url": "https://homebrew.bintray.com/bottles/wget-1.20.3_2.mojave.bottle.tar.gz",
              "sha256": "28f4090610946a4eb207df102d841de23ced0d06ba31cb79e040d883906dcd4f"
            },
            "high_sierra": {
              "url": "https://homebrew.bintray.com/bottles/wget-1.20.3_2.high_sierra.bottle.tar.gz",
              "sha256": "91dd0caca9bd3f38c439d5a7b6f68440c4274945615fae035ff0a369264b8a2f"
            }
          }
        }
      },
      "zsh": {
        "version": "5.7.1",
        "bottle": {
          "cellar": "/usr/local/Cellar",
          "prefix": "/usr/local",
          "files": {
            "catalina": {
              "url": "https://homebrew.bintray.com/bottles/zsh-5.7.1.catalina.bottle.tar.gz",
              "sha256": "a24afee5cc1af2b139b6afb8963992b3fb22a4b9fbfa02402ac17e6bfa66a27a"
            },
            "mojave": {
              "url": "https://homebrew.bintray.com/bottles/zsh-5.7.1.mojave.bottle.tar.gz",
              "sha256": "793d87f67e64a5e01dfdea890af218e4779a2df514d395b956e464129af16fd7"
            },
            "high_sierra": {
              "url": "https://homebrew.bintray.com/bottles/zsh-5.7.1.high_sierra.bottle.tar.gz",
              "sha256": "6656fe9aa5d5cbaff49bc9c1ccf17b7d96d21036ac44c9181bd35c57dc38b450"
            },
            "sierra": {
              "url": "https://homebrew.bintray.com/bottles/zsh-5.7.1.sierra.bottle.tar.gz",
              "sha256": "008dfc844b88fcd61925233b08f0d78b2851bf2901320a5f6ee975da4b8604e3"
            }
          }
        }
      },
      "dart-lang/dart/dart": null,
      "getantibody/tap/antibody": null,
      "miderwong/flutter/flutter": null
    },
    "cask": {
      "docker": {
        "version": "2.1.0.5,40693"
      },
      "java": {
        "version": "13.0.1,9:cec27d702aa74d5a8630c65ae61e4305"
      },
      "postman": {
        "version": "7.13.0"
      },
      "spotify": {
        "version": "latest"
      },
      "visual-studio-code": {
        "version": "1.40.2"
      }
    }
  },
  "system": {
    "macos": {
      "high_sierra": {
        "HOMEBREW_VERSION": "2.2.0",
        "HOMEBREW_PREFIX": "/usr/local",
        "Homebrew/homebrew-core": "b82ebf7f81d0e9790e46d14d0786d666664ace12",
        "CLT": "10.1.0.0.1.1539992718",
        "Xcode": "10.2.1",
        "macOS": "10.13.6"
      }
    }
  }
}